crypt_dir
