Metadata-Version: 2.1
Name: crypt-dir
Version: 1.1.5
Home-page: https://github.com/khanh-nguyen-code/crypt-dir
Author: Nguyen Ngoc Khanh
Author-email: khanh.nguyen.contact@gmail.com
License: MIT
License-File: LICENSE
